{
  "db_name": "PostgreSQL",
  "query": "\n        SELECT id, name, description, is_virtual\n        FROM groups\n        ORDER BY name\n        LIMIT $1 OFFSET $2\n        ",
  "describe": {
    "columns": [
      {
        "ordinal": 0,
        "name": "id",
        "type_info": "Uuid"
      },
      {
        "ordinal": 1,
        "name": "name",
        "type_info": "Varchar"
      },
      {
        "ordinal": 2,
        "name": "description",
        "type_info": "Text"
      },
      {
        "ordinal": 3,
        "name": "is_virtual",
        "type_info": "Bool"
      }
    ],
    "parameters": {
      "Left": [
        "Int8",
        "Int8"
      ]
    },
    "nullable": [
      false,
      false,
      true,
      false
    ]
  },
  "hash": "c9c3a9e8218de62df2cf4cc12a8bdfbe782c3ef97f275c3583aed0e60caaf626"
}
