{
  "db_name": "PostgreSQL",
  "query": "\n        UPDATE groups\n        SET\n            name = COALESCE($1, name),\n            description = COALESCE($2, description)\n        WHERE id = $3\n        RETURNING id, name, description\n        ",
  "describe": {
    "columns": [
      {
        "ordinal": 0,
        "name": "id",
        "type_info": "Uuid"
      },
      {
        "ordinal": 1,
        "name": "name",
        "type_info": "Varchar"
      },
      {
        "ordinal": 2,
        "name": "description",
        "type_info": "Text"
      }
    ],
    "parameters": {
      "Left": [
        "Varchar",
        "Text",
        "Uuid"
      ]
    },
    "nullable": [
      false,
      false,
      true
    ]
  },
  "hash": "b769ba40870969280b6c8a491ae8cdd53f65f6365724461640bb65906cc87504"
}
